algoappdev/__init__.py
algoappdev/apps.py
algoappdev/clients.py
algoappdev/dryruns.py
algoappdev/testing.py
algoappdev/transactions.py
algoappdev/utils.py
algoappdev/data/network_private.json
algoappdev/data/network_private_dev.json
algoappdev/scripts/__init__.py
algoappdev/scripts/make_node.py
algoappdev/scripts/run_node.py
algo_app_dev-0.6.1.dist-info/LICENSE
algo_app_dev-0.6.1.dist-info/METADATA
algo_app_dev-0.6.1.dist-info/WHEEL
algo_app_dev-0.6.1.dist-info/entry_points.txt
algo_app_dev-0.6.1.dist-info/top_level.txt
algo_app_dev-0.6.1.dist-info/RECORD
