Metadata-Version: 2.1
Name: algo-app-dev
Version: 0.6.1
Summary: Utilities to help in the development of PyTeal contracts for Algorand.
Home-page: https://github.com/gmcgoldr/algo-app-dev
Author: Garrin McGoldrick
Author-email: garrin.mcgoldrick@gmail.com
License: UNKNOWN
Project-URL: Bug Tracker, https://github.com/gmcgoldr/algo-app-dev/issues
Platform: UNKNOWN
Classifier: Programming Language :: Python :: 3
Classifier: License :: OSI Approved :: MIT License
Classifier: Operating System :: POSIX :: Linux
Requires-Python: >=3.6
License-File: LICENSE
Requires-Dist: py-algorand-sdk (>=1.8)
Requires-Dist: pyteal (>=0.9)
Requires-Dist: setuptools (>=40)
Provides-Extra: dev
Requires-Dist: pytest ; extra == 'dev'
Requires-Dist: pytest-xdist ; extra == 'dev'
